dff1.v
module dff1(d,reset,clk,q);
	input d,reset,clk;
	output q;
	reg q;
	
	
		always @ ( posedge clk ) 
		begin
		if(reset) begin
		q<=1'b0;
		end
		else begin
			q<=d;
			end
	end
	

endmodule

elevator.v
`include "dff1.v"
module elevator(in,r,g,clk,reset);
	input in,clk,reset;
	output r,g;
	wire q;
	dff1 t1(in,clk,reset,q);
	assign r=~q;
	assign g=q;
	endmodule

elevator_t.v
`include "elevator.v"
module elevator_t;
	reg in,clk,reset;
	wire r,g;

	elevator inst(in,r,g,clk,reset);
	initial


	begin
	$dumpfile("elevator.vcd");
	$dumpvars(0,elevator_t);
			
			reset=1'b1;
			clk=1'b0;
			#4
			in=1'b1;
			reset=1'b0;
			#4
			in=1'b0;

			
			#4
			in=1'b1;
		
			#4
			in=1'b0;
			#4
			in=1'b1;
		
			#4
			in=1'b0;
			#4
			in=1'b1;
		
			#4
			in=1'b0;
			#8 $finish;

			
	end
	always
	#2 clk=~clk;
	initial
	$monitor($time,"input=%d red=%d green=%d",in,r,g);
endmodule

elevator.vcd
$date
	Thu Oct 29 15:26:41 2015
$end
$version
	Icarus Verilog
$end
$timescale
	1s
$end
$scope module elevator_t $end
$var wire 1 ! g $end
$var wire 1 " r $end
$var reg 1 # clk $end
$var reg 1 $ in $end
$var reg 1 % reset $end
$scope module inst $end
$var wire 1 & clk $end
$var wire 1 ! g $end
$var wire 1 ' in $end
$var wire 1 ( q $end
$var wire 1 " r $end
$var wire 1 ) reset $end
$scope module t1 $end
$var wire 1 & clk $end
$var wire 1 ' d $end
$var wire 1 ) reset $end
$var reg 1 * q $end
$upscope $end
$upscope $end
$upscope $end
$enddefinitions $end
#0
$dumpvars
x*
1)
x(
x'
0&
1%
x$
0#
x"
x!
$end
#2
1"
0*
0(
0!
1#
1&
#4
0#
0&
0%
0)
1$
1'
#6
0"
1*
1(
1!
1#
1&
#8
0#
0&
0$
0'
#10
1"
0*
0(
0!
1#
1&
#12
0#
0&
1$
1'
#14
0"
1*
1(
1!
1#
1&
#16
0#
0&
0$
0'
#18
1"
0*
0(
0!
1#
1&
#20
0#
0&
1$
1'
#22
0"
1*
1(
1!
1#
1&
#24
0#
0&
0$
0'
#26
1"
0*
0(
0!
1#
1&
#28
0#
0&
1$
1'
#30
0"
1*
1(
1!
1#
1&
#32
0#
0&
0$
0'
#34
1"
0*
0(
0!
1#
1&
