dff1.v
module dff1(d,reset,clk,q);
	input d,reset,clk;
	output q;
	reg q;
	
	
		always @ ( posedge clk ) 
		begin
		if(reset) begin
		q<=1'b0;
		end
		else begin
			q<=d;
			end
	end
	

endmodule

johnson.v
`include "dff1.v"

module johnson(n0,n1,n2,n3,clk,reset);
    output n0,n1,n2,n3;
    input clk, reset;
    not (qbar,n3);
    dff1 inst3((~n3),reset,clk,n0);
    dff1 inst0(n0,reset,clk,n1);
    dff1 inst1(n1,reset,clk,n2);
    dff1 inst2(n2,reset,clk,n3);
    // dff1 inst3(qbar,reset,clk,n0);
endmodule

johnsonTB.v
`include "johnson.v"

module johnsonTB;
	wire n0, n1, n2, n3;
	reg clk, reset;

	johnson init(n0 ,n1 ,n2 ,n3 ,clk ,reset);

	initial
		begin
		$dumpfile("johnson.vcd");
		$dumpvars(0,johnsonTB);

		reset = 1'b1;
		clk = 1'b0;
		#4

		reset = 1'b0;

		#400 $finish;

		end
	always 
	#2 clk = ~clk;
	initial
	$monitor($time,") clk = %d output = %d %d %d %d",clk,n0,n1,n2,n3);

endmodule

johnson.vcd
$date
	Thu Oct 29 16:48:20 2015
$end
$version
	Icarus Verilog
$end
$timescale
	1s
$end
$scope module johnsonTB $end
$var wire 1 ! n0 $end
$var wire 1 " n1 $end
$var wire 1 # n2 $end
$var wire 1 $ n3 $end
$var reg 1 % clk $end
$var reg 1 & reset $end
$scope module init $end
$var wire 1 ' clk $end
$var wire 1 ! n0 $end
$var wire 1 " n1 $end
$var wire 1 # n2 $end
$var wire 1 $ n3 $end
$var wire 1 ( qbar $end
$var wire 1 ) reset $end
$scope module inst3 $end
$var wire 1 ' clk $end
$var wire 1 * d $end
$var wire 1 ) reset $end
$var reg 1 + q $end
$upscope $end
$scope module inst0 $end
$var wire 1 ' clk $end
$var wire 1 ! d $end
$var wire 1 ) reset $end
$var reg 1 , q $end
$upscope $end
$scope module inst1 $end
$var wire 1 ' clk $end
$var wire 1 " d $end
$var wire 1 ) reset $end
$var reg 1 - q $end
$upscope $end
$scope module inst2 $end
$var wire 1 ' clk $end
$var wire 1 # d $end
$var wire 1 ) reset $end
$var reg 1 . q $end
$upscope $end
$upscope $end
$upscope $end
$enddefinitions $end
#0
$dumpvars
x.
x-
x,
x+
x*
1)
x(
0'
1&
0%
x$
x#
x"
x!
$end
#2
1*
1(
0+
0!
0,
0"
0-
0#
0.
0$
1%
1'
#4
0%
0'
0&
0)
#6
1+
1!
1%
1'
#8
0%
0'
#10
1,
1"
1%
1'
#12
0%
0'
#14
1-
1#
1%
1'
#16
0%
0'
#18
0*
0(
1.
1$
1%
1'
#20
0%
0'
#22
0+
0!
1%
1'
#24
0%
0'
#26
0,
0"
1%
1'
#28
0%
0'
#30
0-
0#
1%
1'
#32
0%
0'
#34
1*
1(
0.
0$
1%
1'
#36
0%
0'
#38
1+
1!
1%
1'
#40
0%
0'
#42
1,
1"
1%
1'
#44
0%
0'
#46
1-
1#
1%
1'
#48
0%
0'
#50
0*
0(
1.
1$
1%
1'
#52
0%
0'
#54
0+
0!
1%
1'
#56
0%
0'
#58
0,
0"
1%
1'
#60
0%
0'
#62
0-
0#
1%
1'
#64
0%
0'
#66
1*
1(
0.
0$
1%
1'
#68
0%
0'
#70
1+
1!
1%
1'
#72
0%
0'
#74
1,
1"
1%
1'
#76
0%
0'
#78
1-
1#
1%
1'
#80
0%
0'
#82
0*
0(
1.
1$
1%
1'
#84
0%
0'
#86
0+
0!
1%
1'
#88
0%
0'
#90
0,
0"
1%
1'
#92
0%
0'
#94
0-
0#
1%
1'
#96
0%
0'
#98
1*
1(
0.
0$
1%
1'
#100
0%
0'
#102
1+
1!
1%
1'
#104
0%
0'
#106
1,
1"
1%
1'
#108
0%
0'
#110
1-
1#
1%
1'
#112
0%
0'
#114
0*
0(
1.
1$
1%
1'
#116
0%
0'
#118
0+
0!
1%
1'
#120
0%
0'
#122
0,
0"
1%
1'
#124
0%
0'
#126
0-
0#
1%
1'
#128
0%
0'
#130
1*
1(
0.
0$
1%
1'
#132
0%
0'
#134
1+
1!
1%
1'
#136
0%
0'
#138
1,
1"
1%
1'
#140
0%
0'
#142
1-
1#
1%
1'
#144
0%
0'
#146
0*
0(
1.
1$
1%
1'
#148
0%
0'
#150
0+
0!
1%
1'
#152
0%
0'
#154
0,
0"
1%
1'
#156
0%
0'
#158
0-
0#
1%
1'
#160
0%
0'
#162
1*
1(
0.
0$
1%
1'
#164
0%
0'
#166
1+
1!
1%
1'
#168
0%
0'
#170
1,
1"
1%
1'
#172
0%
0'
#174
1-
1#
1%
1'
#176
0%
0'
#178
0*
0(
1.
1$
1%
1'
#180
0%
0'
#182
0+
0!
1%
1'
#184
0%
0'
#186
0,
0"
1%
1'
#188
0%
0'
#190
0-
0#
1%
1'
#192
0%
0'
#194
1*
1(
0.
0$
1%
1'
#196
0%
0'
#198
1+
1!
1%
1'
#200
0%
0'
#202
1,
1"
1%
1'
#204
0%
0'
#206
1-
1#
1%
1'
#208
0%
0'
#210
0*
0(
1.
1$
1%
1'
#212
0%
0'
#214
0+
0!
1%
1'
#216
0%
0'
#218
0,
0"
1%
1'
#220
0%
0'
#222
0-
0#
1%
1'
#224
0%
0'
#226
1*
1(
0.
0$
1%
1'
#228
0%
0'
#230
1+
1!
1%
1'
#232
0%
0'
#234
1,
1"
1%
1'
#236
0%
0'
#238
1-
1#
1%
1'
#240
0%
0'
#242
0*
0(
1.
1$
1%
1'
#244
0%
0'
#246
0+
0!
1%
1'
#248
0%
0'
#250
0,
0"
1%
1'
#252
0%
0'
#254
0-
0#
1%
1'
#256
0%
0'
#258
1*
1(
0.
0$
1%
1'
#260
0%
0'
#262
1+
1!
1%
1'
#264
0%
0'
#266
1,
1"
1%
1'
#268
0%
0'
#270
1-
1#
1%
1'
#272
0%
0'
#274
0*
0(
1.
1$
1%
1'
#276
0%
0'
#278
0+
0!
1%
1'
#280
0%
0'
#282
0,
0"
1%
1'
#284
0%
0'
#286
0-
0#
1%
1'
#288
0%
0'
#290
1*
1(
0.
0$
1%
1'
#292
0%
0'
#294
1+
1!
1%
1'
#296
0%
0'
#298
1,
1"
1%
1'
#300
0%
0'
#302
1-
1#
1%
1'
#304
0%
0'
#306
0*
0(
1.
1$
1%
1'
#308
0%
0'
#310
0+
0!
1%
1'
#312
0%
0'
#314
0,
0"
1%
1'
#316
0%
0'
#318
0-
0#
1%
1'
#320
0%
0'
#322
1*
1(
0.
0$
1%
1'
#324
0%
0'
#326
1+
1!
1%
1'
#328
0%
0'
#330
1,
1"
1%
1'
#332
0%
0'
#334
1-
1#
1%
1'
#336
0%
0'
#338
0*
0(
1.
1$
1%
1'
#340
0%
0'
#342
0+
0!
1%
1'
#344
0%
0'
#346
0,
0"
1%
1'
#348
0%
0'
#350
0-
0#
1%
1'
#352
0%
0'
#354
1*
1(
0.
0$
1%
1'
#356
0%
0'
#358
1+
1!
1%
1'
#360
0%
0'
#362
1,
1"
1%
1'
#364
0%
0'
#366
1-
1#
1%
1'
#368
0%
0'
#370
0*
0(
1.
1$
1%
1'
#372
0%
0'
#374
0+
0!
1%
1'
#376
0%
0'
#378
0,
0"
1%
1'
#380
0%
0'
#382
0-
0#
1%
1'
#384
0%
0'
#386
1*
1(
0.
0$
1%
1'
#388
0%
0'
#390
1+
1!
1%
1'
#392
0%
0'
#394
1,
1"
1%
1'
#396
0%
0'
#398
1-
1#
1%
1'
#400
0%
0'
#402
0*
0(
1.
1$
1%
1'
