dLatch.v
module dLatch(out,data,clock,reset);

	output out;
	input data, clock ,reset;

	wire w0, w1, w2, out_bar;

	not (w0, data);
	nand (w1, data, clock);
	nand (w2, w0, clock);
	nor (out, w1, out_bar, reset);
	nor (out_bar, w2, out);

endmodule
/*
module test_bench;
	wire Q;
	reg data, clock, reset;
	// Instantiating module dLatch
	dLatch inst(Q, d, clk, reset);
	initial
		begin
			reset = 1'b1;
			clock = 1'b0;
			//Set delay 
			#4
			data = 1'b0;
			reset = 1'b0;
			//Set delay
			#4
			data = 1'b0;
			#4
			data = 1'b1;
			#4
			data = 1'b0;
			// What does "finish" do ?
			#8 $finish;
		end
		always 
		#2 clock = ~clock;
		initial
		// $display($time," Data = %d, Clock = %d output = %d", data, clock, Q);
		$monitor($time," d = %b q = %b",data,Q);
endmodule*/

siso_tb.v
`include "SISO.v"

module test_bench;
	wire out;
	reg dat, clk, reset;
	// Instantiating module dLatch
	dLatch inst(out, dat, clk, reset);
	initial
		begin
			reset = 1'b1;
			clk = 1'b0;
			//Set delay 
			#4
			dat = 1'b1;
			reset = 1'b0;
			//Set delay
			#4
			dat = 1'b0;
			#4
			dat = 1'b1;
			#4
			dat = 1'b0;
			#4
			dat = 1'b1;
			#4
			dat = 1'b0;
			#4
			dat = 1'b1;
			#4
			dat = 1'b0;
			// What does "finish" do ?
			#20 $finish;
		end
		initial
		begin
			$dumpfile("siso.vcd");
			$dumpvars;
		end
		always 
		#2 clk = ~clk;
		initial
		// $display($time," Data = %d, Clock = %d output = %d", dat, clk, Q);
		$monitor($time," d = %b q = %b",dat,out);
endmodule

SISO.v
`include "dLatch.v"

module SISO(out, sin, clk, reset);
	input sin, clk, reset;
	output out;
	wire w1,w2,w3;

	dLatch l1 (w1, sin, clk, reset);
	dLatch l2 (w2, w1, clk, reset);
	dLatch l3 (w3, w2, clk, reset);
	dLatch l4 (out, w3, clk, reset);

endmodule

siso.vcd
$date
	Thu Oct  8 17:54:30 2015
$end
$version
	Icarus Verilog
$end
$timescale
	1s
$end
$scope module SISO $end
$var wire 1 ! clk $end
$var wire 1 " out $end
$var wire 1 # reset $end
$var wire 1 $ sin $end
$var wire 1 % w1 $end
$var wire 1 & w2 $end
$var wire 1 ' w3 $end
$scope module l1 $end
$var wire 1 ! clock $end
$var wire 1 $ data $end
$var wire 1 % out $end
$var wire 1 ( out_bar $end
$var wire 1 # reset $end
$var wire 1 ) w0 $end
$var wire 1 * w1 $end
$var wire 1 + w2 $end
$upscope $end
$scope module l2 $end
$var wire 1 ! clock $end
$var wire 1 % data $end
$var wire 1 & out $end
$var wire 1 , out_bar $end
$var wire 1 # reset $end
$var wire 1 - w0 $end
$var wire 1 . w1 $end
$var wire 1 / w2 $end
$upscope $end
$scope module l3 $end
$var wire 1 ! clock $end
$var wire 1 & data $end
$var wire 1 ' out $end
$var wire 1 0 out_bar $end
$var wire 1 # reset $end
$var wire 1 1 w0 $end
$var wire 1 2 w1 $end
$var wire 1 3 w2 $end
$upscope $end
$scope module l4 $end
$var wire 1 ! clock $end
$var wire 1 ' data $end
$var wire 1 " out $end
$var wire 1 4 out_bar $end
$var wire 1 # reset $end
$var wire 1 5 w0 $end
$var wire 1 6 w1 $end
$var wire 1 7 w2 $end
$upscope $end
$upscope $end
$scope module test_bench $end
$var wire 1 8 out $end
$var reg 1 9 clk $end
$var reg 1 : dat $end
$var reg 1 ; reset $end
$scope module inst $end
$var wire 1 < clock $end
$var wire 1 = data $end
$var wire 1 8 out $end
$var wire 1 > out_bar $end
$var wire 1 ? reset $end
$var wire 1 @ w0 $end
$var wire 1 A w1 $end
$var wire 1 B w2 $end
$upscope $end
$upscope $end
$enddefinitions $end
#0
$dumpvars
1B
1A
x@
1?
0>
x=
0<
1;
x:
09
08
x7
x6
x5
x4
x3
x2
x1
x0
x/
x.
x-
x,
x+
x*
x)
x(
x'
x&
x%
z$
z#
x"
z!
$end
#2
x>
xA
xB
19
1<
#4
0>
1B
0@
1A
09
0<
0;
0?
1:
1=
#6
18
0A
19
1<
#8
08
1@
1A
09
0<
0:
0=
#10
1>
0B
19
1<
#12
0>
1B
0@
09
0<
1:
1=
#14
18
0A
19
1<
#16
08
1@
1A
09
0<
0:
0=
#18
1>
0B
19
1<
#20
0>
1B
0@
09
0<
1:
1=
#22
18
0A
19
1<
#24
08
1@
1A
09
0<
0:
0=
#26
1>
0B
19
1<
#28
0>
1B
0@
09
0<
1:
1=
#30
18
0A
19
1<
#32
08
1@
1A
09
0<
0:
0=
#34
1>
0B
19
1<
#36
0>
1B
09
0<
#38
1>
0B
19
1<
#40
0>
1B
09
0<
#42
1>
0B
19
1<
#44
0>
1B
09
0<
#46
1>
0B
19
1<
#48
0>
1B
09
0<
#50
1>
0B
19
1<
#52
0>
1B
09
0<
